MANIFEST.in
setup.py
userbase/__init__.py
userbase/base.py
userbase/decorators.py
userbase/exceptions.py
userbase/hooks.py
userbase/scripts.py
userbase/um.py
userbase.egg-info/PKG-INFO
userbase.egg-info/SOURCES.txt
userbase.egg-info/dependency_links.txt
userbase.egg-info/entry_points.txt
userbase.egg-info/not-zip-safe
userbase.egg-info/requires.txt
userbase.egg-info/top_level.txt
userbase/db/__init__.py
userbase/db/users.py
userbase/handlers/__init__.py
userbase/handlers/activation.py
userbase/handlers/forms.py
userbase/handlers/login.py
userbase/handlers/logout.py
userbase/handlers/pw_forgot.py
userbase/handlers/pw_set.py
userbase/handlers/registration.py
userbase/handlers/usereditor.py
userbase/templates/activation.html
userbase/templates/login.html
userbase/templates/login_email.html
userbase/templates/login_username.html
userbase/templates/macros.html
userbase/templates/pw_new.html
userbase/templates/registered.html
userbase/templates/registration.html
userbase/templates/send_activation_code.html
userbase/templates/send_pw_code.html
userbase/templates/editor/add.html
userbase/templates/editor/edit.html
userbase/templates/editor/list.html
userbase/templates/emails/activation_code.html
userbase/templates/emails/activation_code.txt
userbase/templates/emails/pw_code.html
userbase/templates/emails/pw_code.txt
userbase/translations/de/LC_MESSAGES/messages.mo
userbase/translations/de/LC_MESSAGES/messages.po