Metadata-Version: 1.0
Name: userbase
Version: 1.1.1
Summary: Participate User Manager
Home-page: UNKNOWN
Author: COM.lounge
Author-email: info@comlounge.net
License: MIT
Platform: UNKNOWN
